{
  "_class": "symbolInstance",
  "do_objectID": "1BB508EE-763D-4AFD-8E76-1B8AF965A647",
  "exportOptions": {
    "_class": "exportOptions",
    "do_objectID": "58C138BA-C7B2-4F7F-8A65-D878F059C282",
    "exportFormats": [
    ],
    "includedLayerIds": [
    ],
    "layerOptions": 0,
    "shouldTrim": false
  },
  "frame": {
    "_class": "rect",
    "constrainProportions": false,
    "do_objectID": "06117E62-87C7-41FC-81FE-438E612EF272",
    "height": 18,
    "width": 42,
    "x": 322,
    "y": 38
  },
  "horizontalSpacing": 0,
  "isFlippedHorizontal": false,
  "isFlippedVertical": false,
  "isLocked": false,
  "isVisible": true,
  "layerListExpandedType": 0,
  "name": "drop_down Bar",
  "nameIsFixed": false,
  "overrideValues": [
  ],
  "resizingConstraint": 63,
  "resizingType": 0,
  "rotation": 0,
  "scale": 1,
  "shouldBreakMaskChain": false,
  "style": {
    "_class": "style",
    "do_objectID": "26BC1E32-3807-4953-83E5-8CDB3D49BCB3",
    "endDecorationType": 0,
    "miterLimit": 10,
    "startDecorationType": 0
  },
  "symbolID": "277615A7-0FFD-45F2-B184-8EBB133E549F",
  "verticalSpacing": 0
}